{
  "Employee": [
    {
      "ImageSrc": null,
      "ImageTitle": "1.jpg",
      "EmployeeId": 1,
      "Name": "Md Akhash Mahmud",
      "Designation": "Manager",
      "PhoneNo": "01748772199",
      "Age": "26",
      "NationalId": "7802461660",
      "Email": "mdakash85@gmail.com",
      "Address": "Dhaka",
      "image": null,
      "Gender": "Female",
      "City": "Dhaka",
      "Country": "BD",
      "Date": "2022-09-17T13:00:00-05:00"
    },
    {
      "ImageSrc": null,
      "ImageTitle": "9219.png",
      "EmployeeId": 9219,
      "Name": "Amena",
      "Designation": "Cashier",
      "PhoneNo": "01200000000",
      "Age": "27",
      "NationalId": "261425632",
      "Email": "amena@gmail.com",
      "Address": "Demra",
      "image": null,
      "Gender": "Female",
      "City": "Barisal",
      "Country": "BD",
      "Date": "2022-08-24T13:00:00-05:00"
    },
    {
      "ImageSrc": null,
      "ImageTitle": "1269216.jpg",
      "EmployeeId": 1269216,
      "Name": "Md Faruk Hossain",
      "Designation": "Manager",
      "PhoneNo": "01700000000",
      "Age": "26",
      "NationalId": "000000000000",
      "Email": "faruk63@gmail.com",
      "Address": "Mirpur",
      "image": null,
      "Gender": "Male",
      "City": "Dhaka",
      "Country": "BD",
      "Date": "2022-08-24T13:00:00-05:00"
    },
    {
      "ImageSrc": null,
      "ImageTitle": "88886.jpg",
      "EmployeeId": 88886,
      "Name": "jhhjj",
      "Designation": "Manager",
      "PhoneNo": "566656",
      "Age": "58",
      "NationalId": "6445555222",
      "Email": "bvn bv n",
      "Address": "vbnvcnvb",
      "image": null,
      "Gender": "Male",
      "City": "vbb",
      "Country": "b",
      "Date": "2022-08-24T13:00:00-05:00"
    },
    {
      "ImageSrc": null,
      "ImageTitle": "2.JPG",
      "EmployeeId": 2,
      "Name": "Md Saiful",
      "Designation": "Cashier",
      "PhoneNo": "0174565526",
      "Age": "45",
      "NationalId": "6565232255",
      "Email": "saifjul@gmail.com",
      "Address": "Dhaka",
      "image": null,
      "Gender": "Male",
      "City": "Dhaka",
      "Country": "Bangladeshi",
      "Date": "2022-12-13T00:00:00"
    }
  ]
}